digitalhub_runtime_kfp/__init__.py
digitalhub_runtime_kfp/dsl.py
digitalhub_runtime_kfp/entities/__init__.py
digitalhub_runtime_kfp/entities/_base/__init__.py
digitalhub_runtime_kfp/entities/_base/runtime_entity/__init__.py
digitalhub_runtime_kfp/entities/_base/runtime_entity/builder.py
digitalhub_runtime_kfp/entities/_commons/__init__.py
digitalhub_runtime_kfp/entities/_commons/enums.py
digitalhub_runtime_kfp/entities/run/__init__.py
digitalhub_runtime_kfp/entities/run/_base/__init__.py
digitalhub_runtime_kfp/entities/run/_base/entity.py
digitalhub_runtime_kfp/entities/run/_base/spec.py
digitalhub_runtime_kfp/entities/run/_base/status.py
digitalhub_runtime_kfp/entities/run/_base/utils.py
digitalhub_runtime_kfp/entities/run/build/__init__.py
digitalhub_runtime_kfp/entities/run/build/builder.py
digitalhub_runtime_kfp/entities/run/build/entity.py
digitalhub_runtime_kfp/entities/run/build/spec.py
digitalhub_runtime_kfp/entities/run/build/status.py
digitalhub_runtime_kfp/entities/run/pipeline/__init__.py
digitalhub_runtime_kfp/entities/run/pipeline/builder.py
digitalhub_runtime_kfp/entities/run/pipeline/entity.py
digitalhub_runtime_kfp/entities/run/pipeline/spec.py
digitalhub_runtime_kfp/entities/run/pipeline/status.py
digitalhub_runtime_kfp/entities/task/__init__.py
digitalhub_runtime_kfp/entities/task/build/__init__.py
digitalhub_runtime_kfp/entities/task/build/builder.py
digitalhub_runtime_kfp/entities/task/build/entity.py
digitalhub_runtime_kfp/entities/task/build/spec.py
digitalhub_runtime_kfp/entities/task/build/status.py
digitalhub_runtime_kfp/entities/task/pipeline/__init__.py
digitalhub_runtime_kfp/entities/task/pipeline/builder.py
digitalhub_runtime_kfp/entities/task/pipeline/entity.py
digitalhub_runtime_kfp/entities/task/pipeline/spec.py
digitalhub_runtime_kfp/entities/task/pipeline/status.py
digitalhub_runtime_kfp/entities/workflow/__init__.py
digitalhub_runtime_kfp/entities/workflow/kfp/__init__.py
digitalhub_runtime_kfp/entities/workflow/kfp/builder.py
digitalhub_runtime_kfp-0.14.0.dist-info/METADATA
digitalhub_runtime_kfp-0.14.0.dist-info/WHEEL
digitalhub_runtime_kfp-0.14.0.dist-info/licenses/AUTHORS
digitalhub_runtime_kfp-0.14.0.dist-info/licenses/LICENSE
digitalhub_runtime_kfp-0.14.0.dist-info/RECORD
